blackbear/__init__.py
blackbear/core.py
tests/__init__.py
tests/test_methods.py
blackbear-1.0.0.dist-info/AUTHORS.rst
blackbear-1.0.0.dist-info/LICENSE
blackbear-1.0.0.dist-info/METADATA
blackbear-1.0.0.dist-info/WHEEL
blackbear-1.0.0.dist-info/top_level.txt
blackbear-1.0.0.dist-info/RECORD
