Metadata-Version: 2.1
Name: blackbear
Version: 1.0.0
Summary: Standard Library Data and Math Tools
Home-page: https://github.com/cgdeboer/blackbear
Author: Calvin DeBoer
Author-email: cgdeboer@gmail.com
Classifier: Programming Language :: Python :: 3
Classifier: License :: OSI Approved :: MIT License
Classifier: Operating System :: OS Independent
License-File: LICENSE
License-File: AUTHORS.rst
